pagesizey/__init__.py
pagesizey/pagesizey.py
pagesizey-1.0.0.dist-info/METADATA
pagesizey-1.0.0.dist-info/WHEEL
pagesizey-1.0.0.dist-info/licenses/LICENSE
pagesizey-1.0.0.dist-info/RECORD
