Metadata-Version: 2.4
Name: PageSizey
Version: 1.0.0
Summary: A small package to map paper size dimensions to ANSI or ISO page size codes
Project-URL: Homepage, https://patabid.com
Project-URL: Issues, https://github.com/patabid/PageSizey/issues
Author-email: Melvin Newman <melvin@patabid.com>
License-Expression: MIT
License-File: LICENSE
Classifier: Operating System :: OS Independent
Classifier: Programming Language :: Python :: 3
Requires-Python: >=3.9
